{
  "base_monte_carlo": {
    "motor_covariance_scale": 1e-08,
    "n_trials": 24,
    "process_covariance_scale": null,
    "seed": 2323,
    "signal_dependent_scale": 0.02
  },
  "cells": [
    {
      "evaluations": [
        {
          "action_mismatch_to_reference_mean": 0.0,
          "action_mismatch_to_reference_std": 0.0,
          "control_effort_mean": 16.93947357171622,
          "control_effort_std": 0.2513594338544234,
          "cost_mean": 4399.8571580929965,
          "cost_ratio_to_reference_mean": 1.0,
          "cost_ratio_to_reference_std": 0.0,
          "cost_std": 54.44388862383214,
          "deterministic_exact_l2_cost": 11245.971880342271,
          "deterministic_exact_l2_cost_ratio_to_hinf": 1.380346559836211,
          "deterministic_exact_l2_cost_ratio_to_lqr": 1.0,
          "deterministic_gain_relative_error": 0.0,
          "deterministic_gamma_penalized_feasible": false,
          "deterministic_lambda_over_gamma_squared": 1.5551183024132287,
          "deterministic_objective_ratio_to_reference": 1.0,
          "label": "analytical_lqr_reference",
          "peak_forward_velocity_mean": 0.7327252816368658,
          "peak_forward_velocity_std": 0.0061462246696469824,
          "source": "analytical_lqr_reference",
          "terminal_error_mean": 0.0034959285470592344,
          "terminal_error_std": 0.0011580298044153445
        },
        {
          "action_mismatch_to_reference_mean": 0.04734329057521017,
          "action_mismatch_to_reference_std": 0.006583999120048424,
          "control_effort_mean": 16.933052822452325,
          "control_effort_std": 0.1556403342088549,
          "cost_mean": 4401.805985925163,
          "cost_ratio_to_reference_mean": 1.0004877233287583,
          "cost_ratio_to_reference_std": 0.005986914746968855,
          "cost_std": 42.91146385837591,
          "deterministic_exact_l2_cost": 12998.915873112532,
          "deterministic_exact_l2_cost_ratio_to_hinf": 1.5955053949952704,
          "deterministic_exact_l2_cost_ratio_to_lqr": 1.1558730549410647,
          "deterministic_gain_relative_error": 0.979471963294728,
          "deterministic_gamma_penalized_feasible": false,
          "deterministic_lambda_over_gamma_squared": 2.0967915659667837,
          "deterministic_objective_ratio_to_reference": 1.0131700438496394,
          "label": "strong_optimizer_whitened__scratch",
          "peak_forward_velocity_mean": 0.7331476413164504,
          "peak_forward_velocity_std": 0.005951861184657949,
          "source": "deterministic_phase3_scratch_fit",
          "terminal_error_mean": 0.0031348387815473477,
          "terminal_error_std": 0.0013167129027616237
        },
        {
          "action_mismatch_to_reference_mean": 0.07703548370771585,
          "action_mismatch_to_reference_std": 0.004360316855666628,
          "control_effort_mean": 16.582370668538708,
          "control_effort_std": 0.1698512320412852,
          "cost_mean": 4408.963773779808,
          "cost_ratio_to_reference_mean": 1.0021151968218123,
          "cost_ratio_to_reference_std": 0.005788429261662548,
          "cost_std": 42.14698410231992,
          "deterministic_exact_l2_cost": 13029.414630264262,
          "deterministic_exact_l2_cost_ratio_to_hinf": 1.5992488557616324,
          "deterministic_exact_l2_cost_ratio_to_lqr": 1.1585850266120097,
          "deterministic_gain_relative_error": 0.9796046163149528,
          "deterministic_gamma_penalized_feasible": false,
          "deterministic_lambda_over_gamma_squared": 2.063400984959241,
          "deterministic_objective_ratio_to_reference": 1.0154344995185434,
          "label": "strong_optimizer_whitened_block_time__scratch",
          "peak_forward_velocity_mean": 0.7345872766692345,
          "peak_forward_velocity_std": 0.006163465253617773,
          "source": "deterministic_phase3_scratch_fit",
          "terminal_error_mean": 0.0032154845529293948,
          "terminal_error_std": 0.0013009453652345025
        },
        {
          "action_mismatch_to_reference_mean": 8.092006771994972e-05,
          "action_mismatch_to_reference_std": 1.738708621595994e-05,
          "control_effort_mean": 16.93947763013823,
          "control_effort_std": 0.25136532624599267,
          "cost_mean": 4399.857491567704,
          "cost_ratio_to_reference_mean": 1.0000000730634633,
          "cost_ratio_to_reference_std": 1.3455101493938156e-06,
          "cost_std": 54.44492572897487,
          "deterministic_exact_l2_cost": 11245.886736398565,
          "deterministic_exact_l2_cost_ratio_to_hinf": 1.3803361091476412,
          "deterministic_exact_l2_cost_ratio_to_lqr": 0.9999924289385913,
          "deterministic_gain_relative_error": 0.00013085276497793393,
          "deterministic_gamma_penalized_feasible": false,
          "deterministic_lambda_over_gamma_squared": 1.5551095304465856,
          "deterministic_objective_ratio_to_reference": 1.000000000102194,
          "label": "strong_optimizer_whitened__bellman_init",
          "peak_forward_velocity_mean": 0.732725263352699,
          "peak_forward_velocity_std": 0.006146308687203822,
          "source": "deterministic_phase3_preservation_init_fit",
          "terminal_error_mean": 0.003495930105821502,
          "terminal_error_std": 0.0011580498393432533
        },
        {
          "action_mismatch_to_reference_mean": 0.005380414399000808,
          "action_mismatch_to_reference_std": 4.046077847090938e-05,
          "control_effort_mean": 16.933579494671097,
          "control_effort_std": 0.25089016840655975,
          "cost_mean": 4400.085106183389,
          "cost_ratio_to_reference_mean": 1.000051500982908,
          "cost_ratio_to_reference_std": 0.00018398540422179762,
          "cost_std": 54.55995467143862,
          "deterministic_exact_l2_cost": 11248.558179966085,
          "deterministic_exact_l2_cost_ratio_to_hinf": 1.3806640059250348,
          "deterministic_exact_l2_cost_ratio_to_lqr": 1.0002299756438422,
          "deterministic_gain_relative_error": null,
          "deterministic_gamma_penalized_feasible": false,
          "deterministic_lambda_over_gamma_squared": 1.555238631453558,
          "deterministic_objective_ratio_to_reference": null,
          "label": "deterministic_bellman_initialization_raw",
          "peak_forward_velocity_mean": 0.7325593547883715,
          "peak_forward_velocity_std": 0.006145631796705389,
          "source": "deterministic_phase3_initial_controller_only",
          "terminal_error_mean": 0.0035023257748889995,
          "terminal_error_std": 0.0011578972636009848
        }
      ],
      "label": "0.0",
      "monte_carlo": {
        "motor_covariance_scale": 1e-08,
        "n_trials": 24,
        "process_covariance_scale": 0.0,
        "seed": 2323,
        "signal_dependent_scale": 0.02
      },
      "process_covariance_scale": 0.0,
      "verdict": "The released-stochastic evaluation keeps the deterministic Phase 3 interpretation: scratch-like fitted controllers remain behaviorally near in cost but still have substantial action mismatch relative to the analytical reference under the same sampled noise.\nBest scratch stochastic cost ratio is 1.0004877 (strong_optimizer_whitened__scratch), with action mismatch 0.047343291.\nThe preservation-init fit remains indistinguishable from the reference at this Monte Carlo scale: cost ratio 1.0000001, action mismatch 8.0920068e-05.\nThe analytical reference mean cost is 4399.8572 with peak forward velocity 0.73272528.\nThis lane evaluates forward-simulation fidelity only; it does not add a stochastic Bellman objective or parity result."
    },
    {
      "evaluations": [
        {
          "action_mismatch_to_reference_mean": 0.0,
          "action_mismatch_to_reference_std": 0.0,
          "control_effort_mean": 16.94305028372176,
          "control_effort_std": 0.25122451056943723,
          "cost_mean": 4400.890446936825,
          "cost_ratio_to_reference_mean": 1.0,
          "cost_ratio_to_reference_std": 0.0,
          "cost_std": 55.32761807912463,
          "deterministic_exact_l2_cost": 11245.971880342271,
          "deterministic_exact_l2_cost_ratio_to_hinf": 1.380346559836211,
          "deterministic_exact_l2_cost_ratio_to_lqr": 1.0,
          "deterministic_gain_relative_error": 0.0,
          "deterministic_gamma_penalized_feasible": false,
          "deterministic_lambda_over_gamma_squared": 1.5551183024132287,
          "deterministic_objective_ratio_to_reference": 1.0,
          "label": "analytical_lqr_reference",
          "peak_forward_velocity_mean": 0.7327159400687068,
          "peak_forward_velocity_std": 0.006255986264522957,
          "source": "analytical_lqr_reference",
          "terminal_error_mean": 0.0034943270138321743,
          "terminal_error_std": 0.001135346494568535
        },
        {
          "action_mismatch_to_reference_mean": 0.04822000519308484,
          "action_mismatch_to_reference_std": 0.006431989942551369,
          "control_effort_mean": 16.93414486032612,
          "control_effort_std": 0.15283603407137705,
          "cost_mean": 4405.40880909291,
          "cost_ratio_to_reference_mean": 1.0010697863969114,
          "cost_ratio_to_reference_std": 0.0054957827622828075,
          "cost_std": 43.607018274840954,
          "deterministic_exact_l2_cost": 12998.915873112532,
          "deterministic_exact_l2_cost_ratio_to_hinf": 1.5955053949952704,
          "deterministic_exact_l2_cost_ratio_to_lqr": 1.1558730549410647,
          "deterministic_gain_relative_error": 0.979471963294728,
          "deterministic_gamma_penalized_feasible": false,
          "deterministic_lambda_over_gamma_squared": 2.0967915659667837,
          "deterministic_objective_ratio_to_reference": 1.0131700438496394,
          "label": "strong_optimizer_whitened__scratch",
          "peak_forward_velocity_mean": 0.7330702298026283,
          "peak_forward_velocity_std": 0.0060150507682901685,
          "source": "deterministic_phase3_scratch_fit",
          "terminal_error_mean": 0.0031502381265744103,
          "terminal_error_std": 0.0012922945339115914
        },
        {
          "action_mismatch_to_reference_mean": 0.07739343119186234,
          "action_mismatch_to_reference_std": 0.004326275611664428,
          "control_effort_mean": 16.581845555098035,
          "control_effort_std": 0.1658576020553014,
          "cost_mean": 4412.797348864539,
          "cost_ratio_to_reference_mean": 1.0027509533310044,
          "cost_ratio_to_reference_std": 0.005464717051599469,
          "cost_std": 42.533524384766444,
          "deterministic_exact_l2_cost": 13029.414630264262,
          "deterministic_exact_l2_cost_ratio_to_hinf": 1.5992488557616324,
          "deterministic_exact_l2_cost_ratio_to_lqr": 1.1585850266120097,
          "deterministic_gain_relative_error": 0.9796046163149528,
          "deterministic_gamma_penalized_feasible": false,
          "deterministic_lambda_over_gamma_squared": 2.063400984959241,
          "deterministic_objective_ratio_to_reference": 1.0154344995185434,
          "label": "strong_optimizer_whitened_block_time__scratch",
          "peak_forward_velocity_mean": 0.7345121004793631,
          "peak_forward_velocity_std": 0.0062137159139243805,
          "source": "deterministic_phase3_scratch_fit",
          "terminal_error_mean": 0.003227639585891777,
          "terminal_error_std": 0.001294351653227077
        },
        {
          "action_mismatch_to_reference_mean": 8.217710804705124e-05,
          "action_mismatch_to_reference_std": 1.7587422045243754e-05,
          "control_effort_mean": 16.943053691120543,
          "control_effort_std": 0.25123089221904205,
          "cost_mean": 4400.890520324134,
          "cost_ratio_to_reference_mean": 1.000000014466357,
          "cost_ratio_to_reference_std": 1.298011764472601e-06,
          "cost_std": 55.328447993783286,
          "deterministic_exact_l2_cost": 11245.886736398565,
          "deterministic_exact_l2_cost_ratio_to_hinf": 1.3803361091476412,
          "deterministic_exact_l2_cost_ratio_to_lqr": 0.9999924289385913,
          "deterministic_gain_relative_error": 0.00013085276497793393,
          "deterministic_gamma_penalized_feasible": false,
          "deterministic_lambda_over_gamma_squared": 1.5551095304465856,
          "deterministic_objective_ratio_to_reference": 1.000000000102194,
          "label": "strong_optimizer_whitened__bellman_init",
          "peak_forward_velocity_mean": 0.7327159102359767,
          "peak_forward_velocity_std": 0.006256077900953913,
          "source": "deterministic_phase3_preservation_init_fit",
          "terminal_error_mean": 0.0034943253336753846,
          "terminal_error_std": 0.0011353554863163683
        },
        {
          "action_mismatch_to_reference_mean": 0.005382685649213817,
          "action_mismatch_to_reference_std": 4.206752842516598e-05,
          "control_effort_mean": 16.937227052552295,
          "control_effort_std": 0.2508156617266919,
          "cost_mean": 4401.145026405204,
          "cost_ratio_to_reference_mean": 1.0000575221809973,
          "cost_ratio_to_reference_std": 0.00018754575239980393,
          "cost_std": 55.448886647504445,
          "deterministic_exact_l2_cost": 11248.558179966085,
          "deterministic_exact_l2_cost_ratio_to_hinf": 1.3806640059250348,
          "deterministic_exact_l2_cost_ratio_to_lqr": 1.0002299756438422,
          "deterministic_gain_relative_error": null,
          "deterministic_gamma_penalized_feasible": false,
          "deterministic_lambda_over_gamma_squared": 1.555238631453558,
          "deterministic_objective_ratio_to_reference": null,
          "label": "deterministic_bellman_initialization_raw",
          "peak_forward_velocity_mean": 0.7325499668444634,
          "peak_forward_velocity_std": 0.006255422406928027,
          "source": "deterministic_phase3_initial_controller_only",
          "terminal_error_mean": 0.003501151415285575,
          "terminal_error_std": 0.0011347357410562626
        }
      ],
      "label": "0.3",
      "monte_carlo": {
        "motor_covariance_scale": 1e-08,
        "n_trials": 24,
        "process_covariance_scale": 0.3,
        "seed": 2323,
        "signal_dependent_scale": 0.02
      },
      "process_covariance_scale": 0.3,
      "verdict": "The released-stochastic evaluation keeps the deterministic Phase 3 interpretation: scratch-like fitted controllers remain behaviorally near in cost but still have substantial action mismatch relative to the analytical reference under the same sampled noise.\nBest scratch stochastic cost ratio is 1.0010698 (strong_optimizer_whitened__scratch), with action mismatch 0.048220005.\nThe preservation-init fit remains indistinguishable from the reference at this Monte Carlo scale: cost ratio 1, action mismatch 8.2177108e-05.\nThe analytical reference mean cost is 4400.8904 with peak forward velocity 0.73271594.\nThis lane evaluates forward-simulation fidelity only; it does not add a stochastic Bellman objective or parity result."
    },
    {
      "evaluations": [
        {
          "action_mismatch_to_reference_mean": 0.0,
          "action_mismatch_to_reference_std": 0.0,
          "control_effort_mean": 16.94792256750295,
          "control_effort_std": 0.2538568738324507,
          "cost_mean": 4402.846880434483,
          "cost_ratio_to_reference_mean": 1.0,
          "cost_ratio_to_reference_std": 0.0,
          "cost_std": 56.27346999280961,
          "deterministic_exact_l2_cost": 11245.971880342271,
          "deterministic_exact_l2_cost_ratio_to_hinf": 1.380346559836211,
          "deterministic_exact_l2_cost_ratio_to_lqr": 1.0,
          "deterministic_gain_relative_error": 0.0,
          "deterministic_gamma_penalized_feasible": false,
          "deterministic_lambda_over_gamma_squared": 1.5551183024132287,
          "deterministic_objective_ratio_to_reference": 1.0,
          "label": "analytical_lqr_reference",
          "peak_forward_velocity_mean": 0.7327082263448556,
          "peak_forward_velocity_std": 0.00636543282408709,
          "source": "analytical_lqr_reference",
          "terminal_error_mean": 0.0034960292783334894,
          "terminal_error_std": 0.0011222006762601332
        },
        {
          "action_mismatch_to_reference_mean": 0.04995607874094569,
          "action_mismatch_to_reference_std": 0.006329211256609207,
          "control_effort_mean": 16.936802421315985,
          "control_effort_std": 0.15415167334036756,
          "cost_mean": 4415.342841159856,
          "cost_ratio_to_reference_mean": 1.002882098200714,
          "cost_ratio_to_reference_std": 0.00552451947943855,
          "cost_std": 44.572067272713134,
          "deterministic_exact_l2_cost": 12998.915873112532,
          "deterministic_exact_l2_cost_ratio_to_hinf": 1.5955053949952704,
          "deterministic_exact_l2_cost_ratio_to_lqr": 1.1558730549410647,
          "deterministic_gain_relative_error": 0.979471963294728,
          "deterministic_gamma_penalized_feasible": false,
          "deterministic_lambda_over_gamma_squared": 2.0967915659667837,
          "deterministic_objective_ratio_to_reference": 1.0131700438496394,
          "label": "strong_optimizer_whitened__scratch",
          "peak_forward_velocity_mean": 0.7330063078753476,
          "peak_forward_velocity_std": 0.006124363798031318,
          "source": "deterministic_phase3_scratch_fit",
          "terminal_error_mean": 0.0032077654502024166,
          "terminal_error_std": 0.0012879261176721665
        },
        {
          "action_mismatch_to_reference_mean": 0.07815948360799664,
          "action_mismatch_to_reference_std": 0.0043259203117019624,
          "control_effort_mean": 16.58269624620623,
          "control_effort_std": 0.1656080056567066,
          "cost_mean": 4420.84268743139,
          "cost_ratio_to_reference_mean": 1.0041345274575786,
          "cost_ratio_to_reference_std": 0.005657891035379091,
          "cost_std": 43.45358110117884,
          "deterministic_exact_l2_cost": 13029.414630264262,
          "deterministic_exact_l2_cost_ratio_to_hinf": 1.5992488557616324,
          "deterministic_exact_l2_cost_ratio_to_lqr": 1.1585850266120097,
          "deterministic_gain_relative_error": 0.9796046163149528,
          "deterministic_gamma_penalized_feasible": false,
          "deterministic_lambda_over_gamma_squared": 2.063400984959241,
          "deterministic_objective_ratio_to_reference": 1.0154344995185434,
          "label": "strong_optimizer_whitened_block_time__scratch",
          "peak_forward_velocity_mean": 0.7344500243526348,
          "peak_forward_velocity_std": 0.006312646848723939,
          "source": "deterministic_phase3_scratch_fit",
          "terminal_error_mean": 0.0032837159125172666,
          "terminal_error_std": 0.0012937913973636293
        },
        {
          "action_mismatch_to_reference_mean": 8.484962628937212e-05,
          "action_mismatch_to_reference_std": 1.8221731975378276e-05,
          "control_effort_mean": 16.947925918246113,
          "control_effort_std": 0.2538636024539414,
          "cost_mean": 4402.84684574347,
          "cost_ratio_to_reference_mean": 0.9999999902077203,
          "cost_ratio_to_reference_std": 1.279975510041852e-06,
          "cost_std": 56.27418176986603,
          "deterministic_exact_l2_cost": 11245.886736398565,
          "deterministic_exact_l2_cost_ratio_to_hinf": 1.3803361091476412,
          "deterministic_exact_l2_cost_ratio_to_lqr": 0.9999924289385913,
          "deterministic_gain_relative_error": 0.00013085276497793393,
          "deterministic_gamma_penalized_feasible": false,
          "deterministic_lambda_over_gamma_squared": 1.5551095304465856,
          "deterministic_objective_ratio_to_reference": 1.000000000102194,
          "label": "strong_optimizer_whitened__bellman_init",
          "peak_forward_velocity_mean": 0.7327081869759936,
          "peak_forward_velocity_std": 0.0063655296369895574,
          "source": "deterministic_phase3_preservation_init_fit",
          "terminal_error_mean": 0.0034960244781320174,
          "terminal_error_std": 0.0011222017793964404
        },
        {
          "action_mismatch_to_reference_mean": 0.0053847730637006114,
          "action_mismatch_to_reference_std": 4.494677440803671e-05,
          "control_effort_mean": 16.942155654579594,
          "control_effort_std": 0.25349550233241813,
          "cost_mean": 4403.123412008963,
          "cost_ratio_to_reference_mean": 1.0000624621059502,
          "cost_ratio_to_reference_std": 0.00019086748533085808,
          "cost_std": 56.400518329871375,
          "deterministic_exact_l2_cost": 11248.558179966085,
          "deterministic_exact_l2_cost_ratio_to_hinf": 1.3806640059250348,
          "deterministic_exact_l2_cost_ratio_to_lqr": 1.0002299756438422,
          "deterministic_gain_relative_error": null,
          "deterministic_gamma_penalized_feasible": false,
          "deterministic_lambda_over_gamma_squared": 1.555238631453558,
          "deterministic_objective_ratio_to_reference": null,
          "label": "deterministic_bellman_initialization_raw",
          "peak_forward_velocity_mean": 0.7325422148262144,
          "peak_forward_velocity_std": 0.006364902579198191,
          "source": "deterministic_phase3_initial_controller_only",
          "terminal_error_mean": 0.003503201462751626,
          "terminal_error_std": 0.001121249392572335
        }
      ],
      "label": "1.0",
      "monte_carlo": {
        "motor_covariance_scale": 1e-08,
        "n_trials": 24,
        "process_covariance_scale": 1.0,
        "seed": 2323,
        "signal_dependent_scale": 0.02
      },
      "process_covariance_scale": 1.0,
      "verdict": "The released-stochastic evaluation keeps the deterministic Phase 3 interpretation: scratch-like fitted controllers remain behaviorally near in cost but still have substantial action mismatch relative to the analytical reference under the same sampled noise.\nBest scratch stochastic cost ratio is 1.0028821 (strong_optimizer_whitened__scratch), with action mismatch 0.049956079.\nThe preservation-init fit remains indistinguishable from the reference at this Monte Carlo scale: cost ratio 0.99999999, action mismatch 8.4849626e-05.\nThe analytical reference mean cost is 4402.8469 with peak forward velocity 0.73270823.\nThis lane evaluates forward-simulation fidelity only; it does not add a stochastic Bellman objective or parity result."
    },
    {
      "evaluations": [
        {
          "action_mismatch_to_reference_mean": 0.0,
          "action_mismatch_to_reference_std": 0.0,
          "control_effort_mean": 16.959487092891923,
          "control_effort_std": 0.2631692995597011,
          "cost_mean": 4408.128314616206,
          "cost_ratio_to_reference_mean": 1.0,
          "cost_ratio_to_reference_std": 0.0,
          "cost_std": 58.2121597893702,
          "deterministic_exact_l2_cost": 11245.971880342271,
          "deterministic_exact_l2_cost_ratio_to_hinf": 1.380346559836211,
          "deterministic_exact_l2_cost_ratio_to_lqr": 1.0,
          "deterministic_gain_relative_error": 0.0,
          "deterministic_gamma_penalized_feasible": false,
          "deterministic_lambda_over_gamma_squared": 1.5551183024132287,
          "deterministic_objective_ratio_to_reference": 1.0,
          "label": "analytical_lqr_reference",
          "peak_forward_velocity_mean": 0.732695741004566,
          "peak_forward_velocity_std": 0.006576308478845945,
          "source": "analytical_lqr_reference",
          "terminal_error_mean": 0.0035044435235822074,
          "terminal_error_std": 0.0011125108186891034
        },
        {
          "action_mismatch_to_reference_mean": 0.05443027256765963,
          "action_mismatch_to_reference_std": 0.006429542210066127,
          "control_effort_mean": 16.94446971723984,
          "control_effort_std": 0.1631189612907918,
          "cost_mean": 4444.761984676192,
          "cost_ratio_to_reference_mean": 1.0083606374271656,
          "cost_ratio_to_reference_std": 0.007989935178677939,
          "cost_std": 51.233495469884765,
          "deterministic_exact_l2_cost": 12998.915873112532,
          "deterministic_exact_l2_cost_ratio_to_hinf": 1.5955053949952704,
          "deterministic_exact_l2_cost_ratio_to_lqr": 1.1558730549410647,
          "deterministic_gain_relative_error": 0.979471963294728,
          "deterministic_gamma_penalized_feasible": false,
          "deterministic_lambda_over_gamma_squared": 2.0967915659667837,
          "deterministic_objective_ratio_to_reference": 1.0131700438496394,
          "label": "strong_optimizer_whitened__scratch",
          "peak_forward_velocity_mean": 0.7329028446156516,
          "peak_forward_velocity_std": 0.006403319565405994,
          "source": "deterministic_phase3_scratch_fit",
          "terminal_error_mean": 0.003376351259738589,
          "terminal_error_std": 0.0013232566127977486
        },
        {
          "action_mismatch_to_reference_mean": 0.08026391016705528,
          "action_mismatch_to_reference_std": 0.004399792240530449,
          "control_effort_mean": 16.586535088416333,
          "control_effort_std": 0.17114819057886152,
          "cost_mean": 4443.21904691502,
          "cost_ratio_to_reference_mean": 1.0080140896730874,
          "cost_ratio_to_reference_std": 0.007276229102001753,
          "cost_std": 47.63513703647235,
          "deterministic_exact_l2_cost": 13029.414630264262,
          "deterministic_exact_l2_cost_ratio_to_hinf": 1.5992488557616324,
          "deterministic_exact_l2_cost_ratio_to_lqr": 1.1585850266120097,
          "deterministic_gain_relative_error": 0.9796046163149528,
          "deterministic_gamma_penalized_feasible": false,
          "deterministic_lambda_over_gamma_squared": 2.063400984959241,
          "deterministic_objective_ratio_to_reference": 1.0154344995185434,
          "label": "strong_optimizer_whitened_block_time__scratch",
          "peak_forward_velocity_mean": 0.7343495486834279,
          "peak_forward_velocity_std": 0.006576198971905913,
          "source": "deterministic_phase3_scratch_fit",
          "terminal_error_mean": 0.003452650503752837,
          "terminal_error_std": 0.001313804302967961
        },
        {
          "action_mismatch_to_reference_mean": 9.186275320870977e-05,
          "action_mismatch_to_reference_std": 2.036867393780618e-05,
          "control_effort_mean": 16.95949127383037,
          "control_effort_std": 0.2631763371212062,
          "cost_mean": 4408.1283095029075,
          "cost_ratio_to_reference_mean": 0.9999999971720377,
          "cost_ratio_to_reference_std": 1.3426122034606895e-06,
          "cost_std": 58.21277143022615,
          "deterministic_exact_l2_cost": 11245.886736398565,
          "deterministic_exact_l2_cost_ratio_to_hinf": 1.3803361091476412,
          "deterministic_exact_l2_cost_ratio_to_lqr": 0.9999924289385913,
          "deterministic_gain_relative_error": 0.00013085276497793393,
          "deterministic_gamma_penalized_feasible": false,
          "deterministic_lambda_over_gamma_squared": 1.5551095304465856,
          "deterministic_objective_ratio_to_reference": 1.000000000102194,
          "label": "strong_optimizer_whitened__bellman_init",
          "peak_forward_velocity_mean": 0.732695686200636,
          "peak_forward_velocity_std": 0.006576411601802354,
          "source": "deterministic_phase3_preservation_init_fit",
          "terminal_error_mean": 0.0035044327316785607,
          "terminal_error_std": 0.0011125022665232343
        },
        {
          "action_mismatch_to_reference_mean": 0.005388554513541347,
          "action_mismatch_to_reference_std": 5.188852120852892e-05,
          "control_effort_mean": 16.953807152935322,
          "control_effort_std": 0.2628762536578584,
          "cost_mean": 4408.440303730622,
          "cost_ratio_to_reference_mean": 1.0000703833970994,
          "cost_ratio_to_reference_std": 0.00019693466197900832,
          "cost_std": 58.35252626220726,
          "deterministic_exact_l2_cost": 11248.558179966085,
          "deterministic_exact_l2_cost_ratio_to_hinf": 1.3806640059250348,
          "deterministic_exact_l2_cost_ratio_to_lqr": 1.0002299756438422,
          "deterministic_gain_relative_error": null,
          "deterministic_gamma_penalized_feasible": false,
          "deterministic_lambda_over_gamma_squared": 1.555238631453558,
          "deterministic_objective_ratio_to_reference": null,
          "label": "deterministic_bellman_initialization_raw",
          "peak_forward_velocity_mean": 0.732529667503076,
          "peak_forward_velocity_std": 0.006575849058789461,
          "source": "deterministic_phase3_initial_controller_only",
          "terminal_error_mean": 0.0035121695648064007,
          "terminal_error_std": 0.001111123109413272
        }
      ],
      "label": "3.0",
      "monte_carlo": {
        "motor_covariance_scale": 1e-08,
        "n_trials": 24,
        "process_covariance_scale": 3.0,
        "seed": 2323,
        "signal_dependent_scale": 0.02
      },
      "process_covariance_scale": 3.0,
      "verdict": "The released-stochastic evaluation keeps the deterministic Phase 3 interpretation: scratch-like fitted controllers remain behaviorally near in cost but still have substantial action mismatch relative to the analytical reference under the same sampled noise.\nBest scratch stochastic cost ratio is 1.0080141 (strong_optimizer_whitened_block_time__scratch), with action mismatch 0.08026391.\nThe preservation-init fit remains indistinguishable from the reference at this Monte Carlo scale: cost ratio 1, action mismatch 9.1862753e-05.\nThe analytical reference mean cost is 4408.1283 with peak forward velocity 0.73269574.\nThis lane evaluates forward-simulation fidelity only; it does not add a stochastic Bellman objective or parity result."
    }
  ],
  "issue": "dd232cd",
  "non_goals": "No deterministic rollout-recovery objective change, no stochastic training, no robust Bellman objective, and no GRU evaluation.",
  "phase3_issue": "7a459bb",
  "process_covariance_scales": [
    0.0,
    0.3,
    1.0,
    3.0
  ],
  "rerun_metadata": {
    "discretization": "euler",
    "discretization_description": "Forward Euler C&S released-code discretization.",
    "lane": "released_stochastic",
    "lane_description": "Released-code stochastic lane: Euler plant plus sampled sensory, motor/process, and signal-dependent control noise. Bellman parity is not claimed unless a separate stochastic objective is derived.",
    "materializer": "cs_stochastic_phase3_process_noise_sweep",
    "phase_label_policy": "Phase 1 and Phase 3 reruns must report both discretization and lane. Euler deterministic analytical results are canonical after the Euler card lands; ZOH results remain sensitivity/historical unless explicitly promoted."
  },
  "scope": "Released-code stochastic evaluation sweep over explicit process covariance scales. Controllers and common-random-number seeds are held fixed across cells; no stochastic training objective is added.",
  "umbrella": "43e8728"
}
