{
  "adam_common_stage1_matching_settings": [
    {
      "adam_learning_rate": 1e-05,
      "adam_steps": 12
    }
  ],
  "adam_recommendation": "Stage 1 zero-start Adam matches all direct, linear, and affine reference regions. The conservative common setting is steps=12 and lr=1.0e-05; use that for training-facing smoke tests before considering more aggressive per-row settings.",
  "adam_rows": [
    {
      "best_adam_learning_rate": 1e-05,
      "best_adam_steps": 64,
      "best_initialization": "zero",
      "cap_bound_fraction": 0.0,
      "gain": 774.8632563191231,
      "match": true,
      "max_norm_over_cap": 0.8326465487480164,
      "mechanism": "direct_epsilon",
      "mechanism_label": "direct epsilon",
      "optimizer_status": "adam_all_finite",
      "recommendation": "Adam stage 1 is reliable enough for this frozen-audit row.",
      "reference_lambda_multiplier": 2.8284271247461903,
      "reference_lambda_range": "2.59368x-2.82843x; reference=2.82843x",
      "reference_optimizer": "pgd_projected_epsilon",
      "row": "open_loop_small",
      "row_label": "c92 small"
    },
    {
      "best_adam_learning_rate": 1e-05,
      "best_adam_steps": 12,
      "best_initialization": "zero",
      "cap_bound_fraction": 0.0,
      "gain": 585.0014872749325,
      "match": true,
      "max_norm_over_cap": 0.5576916933059692,
      "mechanism": "linear_no_bias",
      "mechanism_label": "closed-loop linear no-bias",
      "optimizer_status": "adam_all_finite",
      "recommendation": "Adam stage 1 is reliable enough for this frozen-audit row.",
      "reference_lambda_multiplier": 2.0,
      "reference_lambda_range": "1.83401x-2x; reference=2x",
      "reference_optimizer": "lbfgsb",
      "row": "open_loop_small",
      "row_label": "c92 small"
    },
    {
      "best_adam_learning_rate": 1e-05,
      "best_adam_steps": 12,
      "best_initialization": "zero",
      "cap_bound_fraction": 0.0,
      "gain": 634.6280464418214,
      "match": true,
      "max_norm_over_cap": 0.612945556640625,
      "mechanism": "affine",
      "mechanism_label": "closed-loop affine",
      "optimizer_status": "adam_all_finite",
      "recommendation": "Adam stage 1 is reliable enough for this frozen-audit row.",
      "reference_lambda_multiplier": 2.1810154653305154,
      "reference_lambda_range": "2x-2.18102x; reference=2.18102x",
      "reference_optimizer": "lbfgsb",
      "row": "open_loop_small",
      "row_label": "c92 small"
    },
    {
      "best_adam_learning_rate": 3e-05,
      "best_adam_steps": 128,
      "best_initialization": "zero",
      "cap_bound_fraction": 0.0,
      "gain": 449.150944899141,
      "match": true,
      "max_norm_over_cap": 0.712648332118988,
      "mechanism": "direct_epsilon",
      "mechanism_label": "direct epsilon",
      "optimizer_status": "adam_all_finite",
      "recommendation": "Adam stage 1 is reliable enough for this frozen-audit row.",
      "reference_lambda_multiplier": 3.084421650815882,
      "reference_lambda_range": "2.82843x-3.08442x; reference=3.08442x",
      "reference_optimizer": "pgd_projected_epsilon",
      "row": "open_loop_moderate",
      "row_label": "c92 moderate"
    },
    {
      "best_adam_learning_rate": 1e-05,
      "best_adam_steps": 12,
      "best_initialization": "zero",
      "cap_bound_fraction": 0.0,
      "gain": 458.09484620560943,
      "match": true,
      "max_norm_over_cap": 0.5301395058631897,
      "mechanism": "linear_no_bias",
      "mechanism_label": "closed-loop linear no-bias",
      "optimizer_status": "adam_all_finite",
      "recommendation": "Adam stage 1 is reliable enough for this frozen-audit row.",
      "reference_lambda_multiplier": 2.0,
      "reference_lambda_range": "1.83401x-2x; reference=2x",
      "reference_optimizer": "lbfgsb",
      "row": "open_loop_moderate",
      "row_label": "c92 moderate"
    },
    {
      "best_adam_learning_rate": 1e-05,
      "best_adam_steps": 12,
      "best_initialization": "zero",
      "cap_bound_fraction": 0.0,
      "gain": 510.62149680591665,
      "match": true,
      "max_norm_over_cap": 0.568103015422821,
      "mechanism": "affine",
      "mechanism_label": "closed-loop affine",
      "optimizer_status": "adam_all_finite",
      "recommendation": "Adam stage 1 is reliable enough for this frozen-audit row.",
      "reference_lambda_multiplier": 2.1810154653305154,
      "reference_lambda_range": "2x-2.18102x; reference=2.18102x",
      "reference_optimizer": "lbfgsb",
      "row": "open_loop_moderate",
      "row_label": "c92 moderate"
    },
    {
      "best_adam_learning_rate": 0.0001,
      "best_adam_steps": 128,
      "best_initialization": "zero",
      "cap_bound_fraction": 0.0,
      "gain": 566.8394377413251,
      "match": true,
      "max_norm_over_cap": 0.8751419186592102,
      "mechanism": "direct_epsilon",
      "mechanism_label": "direct epsilon",
      "optimizer_status": "adam_all_finite",
      "recommendation": "Adam stage 1 is reliable enough for this frozen-audit row.",
      "reference_lambda_multiplier": 2.1810154653305154,
      "reference_lambda_range": "2x-2.18102x; reference=2.18102x",
      "reference_optimizer": "pgd_projected_epsilon",
      "row": "open_loop_stress",
      "row_label": "c92 stress"
    },
    {
      "best_adam_learning_rate": 1e-05,
      "best_adam_steps": 12,
      "best_initialization": "zero",
      "cap_bound_fraction": 0.0,
      "gain": 475.5818562113873,
      "match": true,
      "max_norm_over_cap": 0.5212515592575073,
      "mechanism": "linear_no_bias",
      "mechanism_label": "closed-loop linear no-bias",
      "optimizer_status": "adam_all_finite",
      "recommendation": "Adam stage 1 is reliable enough for this frozen-audit row.",
      "reference_lambda_multiplier": 1.4142135623730951,
      "reference_lambda_range": "1.29684x-1.41421x; reference=1.41421x",
      "reference_optimizer": "lbfgsb",
      "row": "open_loop_stress",
      "row_label": "c92 stress"
    },
    {
      "best_adam_learning_rate": 1e-05,
      "best_adam_steps": 12,
      "best_initialization": "zero",
      "cap_bound_fraction": 0.0,
      "gain": 506.1782503762597,
      "match": true,
      "max_norm_over_cap": 0.5926766991615295,
      "mechanism": "affine",
      "mechanism_label": "closed-loop affine",
      "optimizer_status": "adam_all_finite",
      "recommendation": "Adam stage 1 is reliable enough for this frozen-audit row.",
      "reference_lambda_multiplier": 1.6817928305074292,
      "reference_lambda_range": "1.54221x-1.68179x; reference=1.68179x",
      "reference_optimizer": "lbfgsb",
      "row": "open_loop_stress",
      "row_label": "c92 stress"
    }
  ],
  "dependency": {
    "f3c5db9_adam_commit": "76f7deb",
    "f3c5db9_required_before_final_commit": false,
    "integration_commit": "773ae42",
    "results_f3c5db9_present_on_branch": true
  },
  "direct_4x_sweep_rows": {
    "open_loop_moderate": {
      "cap_bound_fraction": 0.0,
      "diagnostics": {
        "boundary_fraction": 0.0,
        "cap_boundary_fraction": 0.0,
        "energy_lambda": 411726208.0,
        "energy_penalty_term_final_endpoint": 622.8786777423921,
        "energy_penalty_term_selected": 531.6819111960383,
        "energy_penalty_term_zero": 0.0,
        "epsilon_energy_max": 1.2913486671095598e-06,
        "epsilon_energy_mean": 1.2913482123622089e-06,
        "epsilon_norm_max": 0.0011363752419129014,
        "epsilon_norm_mean": 0.0011363751254975796,
        "epsilon_norm_radius_ratio_max": 0.2500000596046448,
        "epsilon_norm_radius_ratio_mean": 0.2500000298023224,
        "inner_objective_after": 4658.602100592004,
        "inner_objective_before": 4480.782897541377,
        "inner_objective_best": 4658.602100592004,
        "inner_objective_final_endpoint": 4436.953773040328,
        "inner_objective_final_endpoint_gap": 221.64832755167572,
        "inner_objective_improvement": 177.81920305062704,
        "inner_objective_nan_seen": false,
        "inner_objective_nonfinite_seen": false,
        "inner_objective_overflow_seen": false,
        "n_steps": 8.0,
        "objective_kind_is_soft_energy": true,
        "penalized_objective_final_endpoint": 4436.953773040328,
        "penalized_objective_selected": 4658.601679321341,
        "penalized_objective_zero": 4480.782897541377,
        "radius_max": 0.004545500036329031,
        "radius_mean": 0.004545500036329031,
        "raw_task_loss_final_endpoint": 5059.83245078272,
        "raw_task_loss_selected": 5190.28359051738,
        "raw_task_loss_zero": 4480.782897541377,
        "safety_cap_boundary_fraction": 0.0,
        "selected_objective_gain_over_zero": 177.81920305062704,
        "selected_vs_final_objective_gap": 221.64832755167572,
        "step_size_fraction_of_l2_radius": 0.25
      },
      "direct_objective_reduction": "mean_i[J_i(epsilon_i) - lambda * E_i(epsilon_i)]",
      "energy_mean": 1.2913482123622089e-06,
      "energy_penalty": 531.6819111960383,
      "finite_status": "finite",
      "lambda": 411726214.59199995,
      "multiplier": 4.0,
      "penalized_gain_over_zero": 177.81920305062704,
      "radius_max": 0.004545500036329031,
      "radius_mean": 0.004545500036329031,
      "raw_loss_gain": 709.5006929760029,
      "selected_epsilon_norm_max": 0.0011363752419129014,
      "selected_epsilon_norm_mean": 0.0011363751254975796,
      "selected_norm_cap_ratio_max": 0.2500000596046448,
      "selected_norm_cap_ratio_mean": 0.2500000298023224
    },
    "open_loop_small": {
      "cap_bound_fraction": 0.0,
      "diagnostics": {
        "boundary_fraction": 0.0,
        "cap_boundary_fraction": 0.0,
        "energy_lambda": 445586176.0,
        "energy_penalty_term_final_endpoint": 788.7151765361909,
        "energy_penalty_term_selected": 575.4068750582039,
        "energy_penalty_term_zero": 0.0,
        "epsilon_energy_max": 1.291348553422722e-06,
        "epsilon_energy_mean": 1.2913480986753711e-06,
        "epsilon_norm_max": 0.0011363751254975796,
        "epsilon_norm_mean": 0.0011363750090822577,
        "epsilon_norm_radius_ratio_max": 0.2500000298023224,
        "epsilon_norm_radius_ratio_mean": 0.25,
        "inner_objective_after": 4652.2750291666425,
        "inner_objective_before": 4420.9607004364525,
        "inner_objective_best": 4652.2750291666425,
        "inner_objective_final_endpoint": 4365.3569145514975,
        "inner_objective_final_endpoint_gap": 286.918114615145,
        "inner_objective_improvement": 231.31432873019003,
        "inner_objective_nan_seen": false,
        "inner_objective_nonfinite_seen": false,
        "inner_objective_overflow_seen": false,
        "n_steps": 8.0,
        "objective_kind_is_soft_energy": true,
        "penalized_objective_final_endpoint": 4365.3569145514975,
        "penalized_objective_selected": 4652.274117335522,
        "penalized_objective_zero": 4420.9607004364525,
        "radius_max": 0.004545500036329031,
        "radius_mean": 0.004545500036329031,
        "raw_task_loss_final_endpoint": 5154.072091087689,
        "raw_task_loss_selected": 5227.680992393725,
        "raw_task_loss_zero": 4420.9607004364525,
        "safety_cap_boundary_fraction": 0.0,
        "selected_objective_gain_over_zero": 231.31432873019003,
        "selected_vs_final_objective_gap": 286.918114615145,
        "step_size_fraction_of_l2_radius": 0.25
      },
      "direct_objective_reduction": "mean_i[J_i(epsilon_i) - lambda * E_i(epsilon_i)]",
      "energy_mean": 1.2913480986753711e-06,
      "energy_penalty": 575.4068750582039,
      "finite_status": "finite",
      "lambda": 445586186.7519999,
      "multiplier": 4.0,
      "penalized_gain_over_zero": 231.31432873019003,
      "radius_max": 0.004545500036329031,
      "radius_mean": 0.004545500036329031,
      "raw_loss_gain": 806.7202919572728,
      "selected_epsilon_norm_max": 0.0011363751254975796,
      "selected_epsilon_norm_mean": 0.0011363750090822577,
      "selected_norm_cap_ratio_max": 0.2500000298023224,
      "selected_norm_cap_ratio_mean": 0.25
    },
    "open_loop_stress": {
      "cap_bound_fraction": 0.0,
      "diagnostics": {
        "boundary_fraction": 0.0,
        "cap_boundary_fraction": 0.0,
        "energy_lambda": 543222464.0,
        "energy_penalty_term_final_endpoint": 344.8250488588219,
        "energy_penalty_term_selected": 701.4894560882999,
        "energy_penalty_term_zero": 0.0,
        "epsilon_energy_max": 1.2913487807963975e-06,
        "epsilon_energy_mean": 1.2913483260490466e-06,
        "epsilon_norm_max": 0.0011363752419129014,
        "epsilon_norm_mean": 0.0011363751254975796,
        "epsilon_norm_radius_ratio_max": 0.2500000596046448,
        "epsilon_norm_radius_ratio_mean": 0.25,
        "inner_objective_after": 4529.378345544169,
        "inner_objective_before": 4507.101414925235,
        "inner_objective_best": 4529.378345544169,
        "inner_objective_final_endpoint": 4446.604610737829,
        "inner_objective_final_endpoint_gap": 82.77373480634014,
        "inner_objective_improvement": 22.276930618933875,
        "inner_objective_nan_seen": false,
        "inner_objective_nonfinite_seen": false,
        "inner_objective_overflow_seen": false,
        "n_steps": 8.0,
        "objective_kind_is_soft_energy": true,
        "penalized_objective_final_endpoint": 4446.604610737829,
        "penalized_objective_selected": 4529.377357428211,
        "penalized_objective_zero": 4507.101414925235,
        "radius_max": 0.004545500036329031,
        "radius_mean": 0.004545500036329031,
        "raw_task_loss_final_endpoint": 4791.429659596651,
        "raw_task_loss_selected": 5230.866813516512,
        "raw_task_loss_zero": 4507.101414925235,
        "safety_cap_boundary_fraction": 0.0,
        "selected_objective_gain_over_zero": 22.276930618933875,
        "selected_vs_final_objective_gap": 82.77373480634014,
        "step_size_fraction_of_l2_radius": 0.25
      },
      "direct_objective_reduction": "mean_i[J_i(epsilon_i) - lambda * E_i(epsilon_i)]",
      "energy_mean": 1.2913483260490466e-06,
      "energy_penalty": 701.4894560882999,
      "finite_status": "finite",
      "lambda": 543222492.288,
      "multiplier": 4.0,
      "penalized_gain_over_zero": 22.276930618933875,
      "radius_max": 0.004545500036329031,
      "radius_mean": 0.004545500036329031,
      "raw_loss_gain": 723.7653985912766,
      "selected_epsilon_norm_max": 0.0011363752419129014,
      "selected_epsilon_norm_mean": 0.0011363751254975796,
      "selected_norm_cap_ratio_max": 0.2500000596046448,
      "selected_norm_cap_ratio_mean": 0.25
    }
  },
  "direct_centers": {
    "open_loop_moderate": {
      "center_lambda": 102931553.64799999,
      "center_source": "per_trial_p90.lambda_beta",
      "transition": {
        "bracket_interpretation": "sweep brackets a cap-to-interior transition",
        "estimate_center_cap_bound_fraction": 1.0,
        "estimate_center_lambda": 102931553.64799999,
        "estimate_center_multiplier": 1.0,
        "estimate_center_norm_cap_ratio_max": 1.0000001192092896,
        "estimate_center_side": "cap_dominated",
        "first_interior_multiplier": 4.0,
        "has_cap_dominated_row": true,
        "has_interior_row": true,
        "interpretation": "p90 estimate lands cap-dominated, but the narrow grid brackets the transition above it",
        "last_cap_dominated_multiplier": 2.0,
        "transition_bracketed": true
      }
    },
    "open_loop_small": {
      "center_lambda": 111396546.68799998,
      "center_source": "per_trial_p90.lambda_beta",
      "transition": {
        "bracket_interpretation": "sweep brackets a cap-to-interior transition",
        "estimate_center_cap_bound_fraction": 1.0,
        "estimate_center_lambda": 111396546.68799998,
        "estimate_center_multiplier": 1.0,
        "estimate_center_norm_cap_ratio_max": 1.0000001192092896,
        "estimate_center_side": "cap_dominated",
        "first_interior_multiplier": 4.0,
        "has_cap_dominated_row": true,
        "has_interior_row": true,
        "interpretation": "p90 estimate lands cap-dominated, but the narrow grid brackets the transition above it",
        "last_cap_dominated_multiplier": 2.0,
        "transition_bracketed": true
      }
    },
    "open_loop_stress": {
      "center_lambda": 135805623.072,
      "center_source": "per_trial_p90.lambda_beta",
      "transition": {
        "bracket_interpretation": "sweep brackets a cap-to-interior transition",
        "estimate_center_cap_bound_fraction": 1.0,
        "estimate_center_lambda": 135805623.072,
        "estimate_center_multiplier": 1.0,
        "estimate_center_norm_cap_ratio_max": 1.0000001192092896,
        "estimate_center_side": "cap_dominated",
        "first_interior_multiplier": 2.0,
        "has_cap_dominated_row": true,
        "has_interior_row": true,
        "interpretation": "p90 estimate lands cap-dominated, but the narrow grid brackets the transition above it",
        "last_cap_dominated_multiplier": 1.0,
        "transition_bracketed": true
      }
    }
  },
  "issue": "27dece3",
  "materialized_at_dependency_state": "f3c5db9_consumed_from_results",
  "parent_umbrella": "54389a4",
  "scale_contract": {
    "cap_fraction_of_15cm": 0.030303333922420437,
    "checkpoint": "final trained_model.eqx for each c92 open_loop no-PGD row",
    "controller_updates": false,
    "epsilon_dim": 6,
    "exact_physical_force_conversion": null,
    "force_conversion_note": "The available code maps broad epsilon into process state coordinates via B_w; it does not expose a direct Newton-scale conversion.",
    "optimized_variables": "epsilon sequence only",
    "reduction": "mean_i[J_i(epsilon_i) - lambda * E_i(epsilon_i)]",
    "safety_cap_l2_radius_15cm": 0.004545500088363065,
    "safety_cap_source": "ofb_6d_no_integrator_gamma_1p4_rollout_radius",
    "trial_batch": "deterministic train batch from run seed and run id"
  },
  "scale_rows": [
    {
      "cap_bound_fraction": 0.0,
      "gain": 700.4077704677684,
      "lambda": 315077014.2553945,
      "max_norm_over_cap": 0.7457857728004456,
      "mechanism": "direct_epsilon",
      "mechanism_label": "direct epsilon",
      "optimizer": "pgd_projected_epsilon",
      "optimizer_status": "bounded_optimizer_materialized_valid_point",
      "row": "open_loop_small",
      "row_label": "c92 small",
      "scale_interpretation": "coordinate perturbation becomes useful and interior near this multiplier; this is the direct frozen-audit scale reference",
      "selected_multiplier": 2.8284271247461903
    },
    {
      "cap_bound_fraction": 0.0,
      "failure_mode": "bracketed_or_valid",
      "gain": 733.7245818081183,
      "lambda": 222793093.37599996,
      "max_norm_over_cap": 0.9112640619277954,
      "mechanism": "linear_no_bias",
      "mechanism_label": "closed-loop linear no-bias",
      "optimizer": "lbfgsb",
      "optimizer_status": "bounded_optimizer_materialized_valid_point",
      "row": "open_loop_small",
      "row_label": "c92 small",
      "scale_interpretation": "full closed-loop no-bias policy has useful interior points in the same lambda region; f3c5db9 found matching zero-start Adam settings",
      "selected_multiplier": 2.0
    },
    {
      "cap_bound_fraction": 0.0,
      "failure_mode": "bracketed_or_valid",
      "gain": 589.4431701733165,
      "lambda": 264947131.81620476,
      "max_norm_over_cap": 0.8067491054534912,
      "mechanism": "linear_no_bias",
      "mechanism_label": "closed-loop linear no-bias",
      "optimizer": "adam",
      "optimizer_status": "bounded_optimizer_materialized_valid_point",
      "row": "open_loop_small",
      "row_label": "c92 small",
      "scale_interpretation": "full closed-loop no-bias policy has useful interior points in the same lambda region; f3c5db9 found matching zero-start Adam settings",
      "selected_multiplier": 2.378414230005442
    },
    {
      "cap_bound_fraction": 0.0,
      "failure_mode": "bracketed_or_valid",
      "gain": 608.2202119301246,
      "lambda": 242957591.11094075,
      "max_norm_over_cap": 0.7519128918647766,
      "mechanism": "affine",
      "mechanism_label": "closed-loop affine",
      "optimizer": "lbfgsb",
      "optimizer_status": "bounded_optimizer_materialized_valid_point",
      "row": "open_loop_small",
      "row_label": "c92 small",
      "scale_interpretation": "affine has useful interior frozen-audit points; f3c5db9 found matching zero-start Adam settings",
      "selected_multiplier": 2.1810154653305154
    },
    {
      "cap_bound_fraction": 0.0,
      "failure_mode": "bracketed_or_valid",
      "gain": 510.17740772264096,
      "lambda": 288926895.9930526,
      "max_norm_over_cap": 0.975540041923523,
      "mechanism": "affine",
      "mechanism_label": "closed-loop affine",
      "optimizer": "adam",
      "optimizer_status": "bounded_optimizer_materialized_valid_point",
      "row": "open_loop_small",
      "row_label": "c92 small",
      "scale_interpretation": "affine has useful interior frozen-audit points; f3c5db9 found matching zero-start Adam settings",
      "selected_multiplier": 2.5936791093020193
    },
    {
      "cap_bound_fraction": 0.0,
      "gain": 1018.1884998240548,
      "lambda": 222793093.37599996,
      "max_norm_over_cap": 0.685043454170227,
      "mechanism": "linear_no_bias",
      "mechanism_label": "closed-loop linear no-bias known direction",
      "optimizer": "line_search_known_direction",
      "optimizer_status": "reference_direction_only",
      "row": "open_loop_small",
      "row_label": "c92 small",
      "scale_interpretation": "known-direction expressivity check only; useful for sanity, not a training inner-optimizer recommendation",
      "selected_multiplier": 2.0
    },
    {
      "cap_bound_fraction": 1.0,
      "gain": 1300.1145074868246,
      "lambda": 222793093.37599996,
      "max_norm_over_cap": 1.0976871252059937,
      "mechanism": "affine",
      "mechanism_label": "closed-loop affine known direction",
      "optimizer": "line_search_known_direction",
      "optimizer_status": "reference_direction_only",
      "row": "open_loop_small",
      "row_label": "c92 small",
      "scale_interpretation": "known-direction expressivity check only; useful for sanity, not a training inner-optimizer recommendation",
      "selected_multiplier": 2.0
    },
    {
      "cap_bound_fraction": 0.0,
      "gain": 383.9295150068292,
      "lambda": 317484312.62400764,
      "max_norm_over_cap": 0.49209436774253845,
      "mechanism": "direct_epsilon",
      "mechanism_label": "direct epsilon",
      "optimizer": "pgd_projected_epsilon",
      "optimizer_status": "bounded_optimizer_materialized_valid_point",
      "row": "open_loop_moderate",
      "row_label": "c92 moderate",
      "scale_interpretation": "coordinate perturbation becomes useful and interior near this multiplier; this is the direct frozen-audit scale reference",
      "selected_multiplier": 3.084421650815882
    },
    {
      "cap_bound_fraction": 0.0,
      "failure_mode": "bracketed_or_valid",
      "gain": 539.3814116677813,
      "lambda": 205863107.29599997,
      "max_norm_over_cap": 0.8934890031814575,
      "mechanism": "linear_no_bias",
      "mechanism_label": "closed-loop linear no-bias",
      "optimizer": "lbfgsb",
      "optimizer_status": "bounded_optimizer_materialized_valid_point",
      "row": "open_loop_moderate",
      "row_label": "c92 moderate",
      "scale_interpretation": "full closed-loop no-bias policy has useful interior points in the same lambda region; f3c5db9 found matching zero-start Adam settings",
      "selected_multiplier": 2.0
    },
    {
      "cap_bound_fraction": 0.0,
      "failure_mode": "bracketed_or_valid",
      "gain": 421.64057660485105,
      "lambda": 244813871.91297174,
      "max_norm_over_cap": 0.6837198734283447,
      "mechanism": "linear_no_bias",
      "mechanism_label": "closed-loop linear no-bias",
      "optimizer": "adam",
      "optimizer_status": "bounded_optimizer_materialized_valid_point",
      "row": "open_loop_moderate",
      "row_label": "c92 moderate",
      "scale_interpretation": "full closed-loop no-bias policy has useful interior points in the same lambda region; f3c5db9 found matching zero-start Adam settings",
      "selected_multiplier": 2.378414230005442
    },
    {
      "cap_bound_fraction": 0.0,
      "failure_mode": "bracketed_or_valid",
      "gain": 583.2711128294213,
      "lambda": 224495310.3767856,
      "max_norm_over_cap": 0.8653865456581116,
      "mechanism": "affine",
      "mechanism_label": "closed-loop affine",
      "optimizer": "lbfgsb",
      "optimizer_status": "bounded_optimizer_materialized_valid_point",
      "row": "open_loop_moderate",
      "row_label": "c92 moderate",
      "scale_interpretation": "affine has useful interior frozen-audit points; f3c5db9 found matching zero-start Adam settings",
      "selected_multiplier": 2.1810154653305154
    },
    {
      "cap_bound_fraction": null,
      "failure_mode": "mixed_invalid_or_nonmonotone",
      "gain": null,
      "lambda": null,
      "max_norm_over_cap": null,
      "mechanism": "affine",
      "mechanism_label": "closed-loop affine",
      "optimizer": "adam",
      "optimizer_status": "no_valid_point",
      "row": "open_loop_moderate",
      "row_label": "c92 moderate",
      "scale_interpretation": "affine has useful interior frozen-audit points; f3c5db9 found matching zero-start Adam settings",
      "selected_multiplier": null
    },
    {
      "cap_bound_fraction": 0.0,
      "gain": 768.9873755131403,
      "lambda": 205863107.29599997,
      "max_norm_over_cap": 0.7000884413719177,
      "mechanism": "linear_no_bias",
      "mechanism_label": "closed-loop linear no-bias known direction",
      "optimizer": "line_search_known_direction",
      "optimizer_status": "reference_direction_only",
      "row": "open_loop_moderate",
      "row_label": "c92 moderate",
      "scale_interpretation": "known-direction expressivity check only; useful for sanity, not a training inner-optimizer recommendation",
      "selected_multiplier": 2.0
    },
    {
      "cap_bound_fraction": 1.0,
      "gain": 1180.3630317759098,
      "lambda": 205863107.29599997,
      "max_norm_over_cap": 1.2274903059005737,
      "mechanism": "affine",
      "mechanism_label": "closed-loop affine known direction",
      "optimizer": "line_search_known_direction",
      "optimizer_status": "reference_direction_only",
      "row": "open_loop_moderate",
      "row_label": "c92 moderate",
      "scale_interpretation": "known-direction expressivity check only; useful for sanity, not a training inner-optimizer recommendation",
      "selected_multiplier": 2.0
    },
    {
      "cap_bound_fraction": 0.0,
      "gain": 489.9115646642904,
      "lambda": 296194164.19887865,
      "max_norm_over_cap": 0.7454544901847839,
      "mechanism": "direct_epsilon",
      "mechanism_label": "direct epsilon",
      "optimizer": "pgd_projected_epsilon",
      "optimizer_status": "bounded_optimizer_materialized_valid_point",
      "row": "open_loop_stress",
      "row_label": "c92 stress",
      "scale_interpretation": "coordinate perturbation becomes useful and interior near this multiplier; this is the direct frozen-audit scale reference",
      "selected_multiplier": 2.1810154653305154
    },
    {
      "cap_bound_fraction": 0.0,
      "failure_mode": "bracketed_or_valid",
      "gain": 541.7943738009353,
      "lambda": 192058153.99495092,
      "max_norm_over_cap": 0.8306800723075867,
      "mechanism": "linear_no_bias",
      "mechanism_label": "closed-loop linear no-bias",
      "optimizer": "lbfgsb",
      "optimizer_status": "bounded_optimizer_materialized_valid_point",
      "row": "open_loop_stress",
      "row_label": "c92 stress",
      "scale_interpretation": "full closed-loop no-bias policy has useful interior points in the same lambda region; f3c5db9 found matching zero-start Adam settings",
      "selected_multiplier": 1.4142135623730951
    },
    {
      "cap_bound_fraction": 0.0,
      "failure_mode": "bracketed_or_valid",
      "gain": 449.57300131070133,
      "lambda": 228396923.22508392,
      "max_norm_over_cap": 0.7451973557472229,
      "mechanism": "linear_no_bias",
      "mechanism_label": "closed-loop linear no-bias",
      "optimizer": "adam",
      "optimizer_status": "bounded_optimizer_materialized_valid_point",
      "row": "open_loop_stress",
      "row_label": "c92 stress",
      "scale_interpretation": "full closed-loop no-bias policy has useful interior points in the same lambda region; f3c5db9 found matching zero-start Adam settings",
      "selected_multiplier": 1.6817928305074292
    },
    {
      "cap_bound_fraction": 0.0,
      "failure_mode": "bracketed_or_valid",
      "gain": 524.9614716401084,
      "lambda": 228396923.22508392,
      "max_norm_over_cap": 0.8532520532608032,
      "mechanism": "affine",
      "mechanism_label": "closed-loop affine",
      "optimizer": "lbfgsb",
      "optimizer_status": "bounded_optimizer_materialized_valid_point",
      "row": "open_loop_stress",
      "row_label": "c92 stress",
      "scale_interpretation": "affine has useful interior frozen-audit points; f3c5db9 found matching zero-start Adam settings",
      "selected_multiplier": 1.6817928305074292
    },
    {
      "cap_bound_fraction": 0.0,
      "failure_mode": "bracketed_or_valid",
      "gain": 401.22119798307085,
      "lambda": 249068610.89390716,
      "max_norm_over_cap": 0.9095777869224548,
      "mechanism": "affine",
      "mechanism_label": "closed-loop affine",
      "optimizer": "adam",
      "optimizer_status": "bounded_optimizer_materialized_valid_point",
      "row": "open_loop_stress",
      "row_label": "c92 stress",
      "scale_interpretation": "affine has useful interior frozen-audit points; f3c5db9 found matching zero-start Adam settings",
      "selected_multiplier": 1.8340080864093424
    },
    {
      "cap_bound_fraction": 0.0,
      "gain": 349.0662062682359,
      "lambda": 271611246.144,
      "max_norm_over_cap": 0.5166273713111877,
      "mechanism": "linear_no_bias",
      "mechanism_label": "closed-loop linear no-bias known direction",
      "optimizer": "line_search_known_direction",
      "optimizer_status": "reference_direction_only",
      "row": "open_loop_stress",
      "row_label": "c92 stress",
      "scale_interpretation": "known-direction expressivity check only; useful for sanity, not a training inner-optimizer recommendation",
      "selected_multiplier": 2.0
    },
    {
      "cap_bound_fraction": 0.0,
      "gain": 212.48007019353645,
      "lambda": 271611246.144,
      "max_norm_over_cap": 0.4024600088596344,
      "mechanism": "affine",
      "mechanism_label": "closed-loop affine known direction",
      "optimizer": "line_search_known_direction",
      "optimizer_status": "reference_direction_only",
      "row": "open_loop_stress",
      "row_label": "c92 stress",
      "scale_interpretation": "known-direction expressivity check only; useful for sanity, not a training inner-optimizer recommendation",
      "selected_multiplier": 2.0
    }
  ],
  "schema_version": "rlrmp.scale_sanity_spec_lock.v1",
  "source_experiment": "c92ebd8",
  "source_results": {
    "closed_loop_policy_audit": "results/3b850d6/closed_loop_policy_audit.json",
    "critical_lambda_search": "results/1697bdc/critical_lambda_search.json",
    "direct_lambda": "results/093d949/soft_lambda_sweep.json",
    "frozen_adam_tuning": "results/f3c5db9/frozen_adam_audit_tuning.json"
  },
  "training_candidates": [
    {
      "adam_learning_rate": 1e-05,
      "adam_match_by_c92_row": {
        "open_loop_moderate": true,
        "open_loop_small": true,
        "open_loop_stress": true
      },
      "adam_steps": 12,
      "lambda_multiplier_by_c92_row": {
        "open_loop_moderate": 3.084421650815882,
        "open_loop_small": 2.8284271247461903,
        "open_loop_stress": 2.1810154653305154
      },
      "mechanism": "direct_epsilon",
      "notes": "No launch approved. f3c5db9 supports this as a training-facing smoke-test candidate with the conservative common Adam setting.",
      "reference_optimizer": "pgd_projected_epsilon",
      "row_id": "direct_epsilon_calibrated",
      "status": "candidate_no_launch_adam_smoke",
      "training_inner_optimizer": "zero_start_adam"
    },
    {
      "adam_learning_rate": 1e-05,
      "adam_match_by_c92_row": {
        "open_loop_moderate": true,
        "open_loop_small": true,
        "open_loop_stress": true
      },
      "adam_steps": 12,
      "lambda_multiplier_by_c92_row": {
        "open_loop_moderate": 2.0,
        "open_loop_small": 2.0,
        "open_loop_stress": 1.4142135623730951
      },
      "mechanism": "linear_no_bias",
      "notes": "No launch approved. f3c5db9 supports this as a training-facing smoke-test candidate with the conservative common Adam setting.",
      "reference_optimizer": "lbfgsb",
      "row_id": "linear_no_bias_calibrated",
      "status": "candidate_no_launch_adam_smoke",
      "training_inner_optimizer": "zero_start_adam"
    },
    {
      "adam_learning_rate": 1e-05,
      "adam_match_by_c92_row": {
        "open_loop_moderate": true,
        "open_loop_small": true,
        "open_loop_stress": true
      },
      "adam_steps": 12,
      "lambda_multiplier_by_c92_row": {
        "open_loop_moderate": 2.1810154653305154,
        "open_loop_small": 2.1810154653305154,
        "open_loop_stress": 1.6817928305074292
      },
      "mechanism": "affine",
      "notes": "No launch approved. f3c5db9 supports this as a training-facing smoke-test candidate with the conservative common Adam setting.",
      "reference_optimizer": "lbfgsb",
      "row_id": "affine_calibrated",
      "status": "candidate_no_launch_adam_smoke",
      "training_inner_optimizer": "zero_start_adam"
    },
    {
      "adam_learning_rate": 1e-05,
      "adam_match_by_c92_row": {
        "open_loop_moderate": true,
        "open_loop_small": true,
        "open_loop_stress": true
      },
      "adam_steps": 12,
      "lambda_multiplier_by_c92_row": {
        "open_loop_moderate": 2.1810154653305154,
        "open_loop_small": 2.1810154653305154,
        "open_loop_stress": 1.6817928305074292
      },
      "mechanism": "affine",
      "notes": "Use future benchmark issue 2e60620 only if Adam fails during training or affine remains unreliable despite the frozen-audit match.",
      "reference_optimizer": "lbfgsb",
      "row_id": "fallback_benchmark_if_training_unreliable",
      "status": "future_path_only",
      "training_inner_optimizer": "adam_vs_optax_lbfgs_benchmark"
    }
  ]
}
